MANIFEST.in
README.md
setup.cfg
setup.py
iparser/__init__.py
iparser/iparser.py
iparser/main.py
iparser/server.py
iparser.egg-info/PKG-INFO
iparser.egg-info/SOURCES.txt
iparser.egg-info/dependency_links.txt
iparser.egg-info/entry_points.txt
iparser.egg-info/requires.txt
iparser.egg-info/top_level.txt
iparser/common/__init__.py
iparser/common/config.py
iparser/common/savable.py
iparser/common/utils.py
iparser/parser/__init__.py
iparser/parser/biaffine_parser.py
iparser/parser/dep_parser.py
iparser/parser/parser_config.py
iparser/parser/common/__init__.py
iparser/parser/common/data.py
iparser/parser/common/k_means.py
iparser/parser/common/tarjan.py
iparser/parser/common/utils.py
iparser/parser/evaluate/__init__.py
iparser/parser/evaluate/evaluate.py
iparser/static/.DS_Store
iparser/static/__init__.py
iparser/static/index.html
iparser/static/__pycache__/__init__.cpython-36.pyc
iparser/tagger/BiLSTM_CRF.py
iparser/tagger/__init__.py
iparser/tagger/corpus.py
iparser/tagger/pos_tagger.py
iparser/tagger/segmenter.py
iparser/tagger/tagger.py
iparser/tagger/tagger_config.py
tests/load_command.py
tests/test_iparser.py
tests/test_load_package_ptb.py
tests/test_parser.py
tests/test_segmenter.py
tests/test_server.py
tests/test_tagger.py
tests/train_parser.py
tests/train_segmenter.py
tests/train_tagger.py