Metadata-Version: 1.1
Name: iparser
Version: 0.1.8
Summary: Integrated and Industrial Strength Dependency Parser
Home-page: https://github.com/hankcs/iparser
Author: hankcs
Author-email: hankcshe@gmail.com
License: UNKNOWN
Keywords: dependency parser
Platform: UNKNOWN
Classifier: Intended Audience :: Developers
Classifier: Topic :: Utilities
Classifier: Natural Language :: English
Classifier: Operating System :: OS Independent
Classifier: Programming Language :: Python :: 3
